jupyter_quizz/__init__.py
jupyter_quizz/_version.py
jupyter_quizz/handlers.py
jupyter_quizz/tests/__init__.py
jupyter_quizz/tests/test_handlers.py
jupyter_quizz-0.0.3.data/data/etc/jupyter/jupyter_notebook_config.d/jupyter_quizz.json
jupyter_quizz-0.0.3.data/data/etc/jupyter/jupyter_server_config.d/jupyter_quizz.json
jupyter_quizz-0.0.3.data/data/share/jupyter/labextensions/@datalayer/jupyter-quizz/build_log.json
jupyter_quizz-0.0.3.data/data/share/jupyter/labextensions/@datalayer/jupyter-quizz/package.json
jupyter_quizz-0.0.3.data/data/share/jupyter/labextensions/@datalayer/jupyter-quizz/schemas/@datalayer/jupyter-quizz/package.json.orig
jupyter_quizz-0.0.3.data/data/share/jupyter/labextensions/@datalayer/jupyter-quizz/schemas/@datalayer/jupyter-quizz/plugin.json
jupyter_quizz-0.0.3.data/data/share/jupyter/labextensions/@datalayer/jupyter-quizz/static/lib_index_js.3d6364a2374bd17101bb.js
jupyter_quizz-0.0.3.data/data/share/jupyter/labextensions/@datalayer/jupyter-quizz/static/lib_index_js.3d6364a2374bd17101bb.js.map
jupyter_quizz-0.0.3.data/data/share/jupyter/labextensions/@datalayer/jupyter-quizz/static/remoteEntry.68534dfc2538adbda165.js
jupyter_quizz-0.0.3.data/data/share/jupyter/labextensions/@datalayer/jupyter-quizz/static/remoteEntry.68534dfc2538adbda165.js.map
jupyter_quizz-0.0.3.data/data/share/jupyter/labextensions/@datalayer/jupyter-quizz/static/style.js
jupyter_quizz-0.0.3.data/data/share/jupyter/labextensions/@datalayer/jupyter-quizz/static/style_index_js.bec41a4e9c8360c5416d.js
jupyter_quizz-0.0.3.data/data/share/jupyter/labextensions/@datalayer/jupyter-quizz/static/style_index_js.bec41a4e9c8360c5416d.js.map
jupyter_quizz-0.0.3.data/data/share/jupyter/labextensions/@datalayer/jupyter-quizz/static/vendors-node_modules_css-loader_dist_runtime_api_js-node_modules_css-loader_dist_runtime_cssW-72eba1.ed1f8bd19a37ec78f7fc.js
jupyter_quizz-0.0.3.dist-info/METADATA
jupyter_quizz-0.0.3.dist-info/WHEEL
jupyter_quizz-0.0.3.dist-info/licenses/LICENSE
jupyter_quizz-0.0.3.dist-info/RECORD
